pypowerautomate/__init__.py
pypowerautomate/__main__.py
pypowerautomate/actions/__init__.py
pypowerautomate/actions/actions.py
pypowerautomate/actions/approval.py
pypowerautomate/actions/base.py
pypowerautomate/actions/condition.py
pypowerautomate/actions/dataoperation.py
pypowerautomate/actions/dropbox.py
pypowerautomate/actions/flowmanagement.py
pypowerautomate/actions/http.py
pypowerautomate/actions/outlook365.py
pypowerautomate/actions/sharepoint.py
pypowerautomate/actions/statements.py
pypowerautomate/actions/teams.py
pypowerautomate/actions/time.py
pypowerautomate/actions/variable.py
pypowerautomate/connections/__init__.py
pypowerautomate/connections/connections.py
pypowerautomate/connections/connectors.py
pypowerautomate/flow/__init__.py
pypowerautomate/flow/flow.py
pypowerautomate/package/__init__.py
pypowerautomate/package/package.py
pypowerautomate/triggers/__init__.py
pypowerautomate/triggers/trigger.py
pypowerautomate-1.0.dist-info/METADATA
pypowerautomate-1.0.dist-info/WHEEL
pypowerautomate-1.0.dist-info/licenses/LICENSE
pypowerautomate-1.0.dist-info/RECORD
