Metadata-Version: 2.3
Name: PyPowerAutomate
Version: 1.0
Summary: Library to generate Power Automate Flow, Actions, and Legacy packages
Project-URL: Homepage, https://github.com/NTT-Security-Japan/PyPowerAutomate
Project-URL: Issues, https://github.com/NTT-Security-Japan/PyPowerAutomate/issues
Project-URL: Blog, https://jp.security.ntt/tech_blog
Author: Tomoaki Tani
License: Copyright 2024 NTT Security (Japan) KK
License-File: LICENSE
Keywords: PowerAutomate,RPA
Classifier: License :: OSI Approved :: BSD License
Classifier: Operating System :: OS Independent
Classifier: Programming Language :: Python :: 3
Requires-Python: >=3.10
